wordlookup/__init__.py
wordlookup/cli.py
wordlookup-0.1.2.dist-info/METADATA
wordlookup-0.1.2.dist-info/WHEEL
wordlookup-0.1.2.dist-info/entry_points.txt
wordlookup-0.1.2.dist-info/licenses/LICENSE
wordlookup-0.1.2.dist-info/licenses/NOTICE
wordlookup-0.1.2.dist-info/RECORD
