Metadata-Version: 2.4
Name: wordlookup
Version: 0.1.2
Summary: Fetches and prints definitions for a given word
Project-URL: Repository, https://github.com/thisdavej/wordlookup
Author-email: Dave Johnson <dave@thisdavej.com>
License-File: LICENSE
License-File: NOTICE
Requires-Python: >=3.13
Requires-Dist: httpx>=0.28.1
